graphtage/__init__.py
graphtage/__main__.py
graphtage/ast.py
graphtage/bounds.py
graphtage/builder.py
graphtage/constraints.py
graphtage/csv.py
graphtage/dataclasses.py
graphtage/debug.py
graphtage/edits.py
graphtage/expressions.py
graphtage/fibonacci.py
graphtage/formatter.py
graphtage/graphtage.py
graphtage/json.py
graphtage/levenshtein.py
graphtage/matching.py
graphtage/multiset.py
graphtage/object_set.py
graphtage/pickle.py
graphtage/plist.py
graphtage/printer.py
graphtage/progress.py
graphtage/pydiff.py
graphtage/search.py
graphtage/sequences.py
graphtage/tree.py
graphtage/utils.py
graphtage/version.py
graphtage/xml.py
graphtage/yaml.py
graphtage-0.3.1.dist-info/LICENSE
graphtage-0.3.1.dist-info/METADATA
graphtage-0.3.1.dist-info/WHEEL
graphtage-0.3.1.dist-info/entry_points.txt
graphtage-0.3.1.dist-info/top_level.txt
graphtage-0.3.1.dist-info/RECORD
