Metadata-Version: 2.1
Name: graphtage
Version: 0.3.1
Summary: A utility to diff tree-like files such as JSON and XML.
Home-page: https://github.com/trailofbits/graphtage
Author: Trail of Bits
License: LGPL-3.0-or-later
Project-URL: Documentation, https://trailofbits.github.io/graphtage
Project-URL: Source, https://github.com/trailofbits/graphtage
Project-URL: Tracker, https://github.com/trailofbits/graphtage/issues
Classifier: Development Status :: 4 - Beta
Classifier: Environment :: Console
Classifier: Intended Audience :: Science/Research
Classifier: License :: OSI Approved :: GNU Lesser General Public License v3 or later (LGPLv3+)
Classifier: Programming Language :: Python :: 3 :: Only
Classifier: Topic :: Utilities
Requires-Python: >=3.8
License-File: LICENSE
Requires-Dist: colorama
Requires-Dist: fickling >=0.0.8
Requires-Dist: intervaltree
Requires-Dist: json5 ==0.9.5
Requires-Dist: numpy >=1.19.4
Requires-Dist: PyYAML
Requires-Dist: scipy >=1.4.0
Requires-Dist: tqdm
Requires-Dist: typing-extensions >=3.7.4.3
Provides-Extra: dev
Requires-Dist: flake8 ; extra == 'dev'
Requires-Dist: Sphinx ; extra == 'dev'
Requires-Dist: pytest ; extra == 'dev'
Requires-Dist: sphinx-rtd-theme ==1.2.2 ; extra == 'dev'
Requires-Dist: twine ; extra == 'dev'
Requires-Dist: importlib-metadata <5 ; (python_version == "3.7") and extra == 'dev'
